MANIFEST.in
setup.py
flexipage/__init__.py
flexipage/admin.py
flexipage/forms.py
flexipage/models.py
flexipage/page_processors.py
flexipage/templatetags.py
flexipage/utils.py
flexipage/views.py
flexipage/static/js/admin/save_modelform_onchange.js
flexipage/templates/flexipage/start.html
mezzanine_flexipage.egg-info/PKG-INFO
mezzanine_flexipage.egg-info/SOURCES.txt
mezzanine_flexipage.egg-info/dependency_links.txt
mezzanine_flexipage.egg-info/not-zip-safe
mezzanine_flexipage.egg-info/requires.txt
mezzanine_flexipage.egg-info/top_level.txt