Metadata-Version: 1.0
Name: mezzanine-flexipage
Version: 0.2.0
Summary: An extension to the Mezzanine Content Management Platform designed to make it easy for template designers to add and remove content areas simply by adding or removing variables from a template.
Home-page: http://github.com/mrmagooey/flexipage
Author: Peter Davis
Author-email: peter.davis8@gmail.com
License: MIT
Platform: UNKNOWN
Classifier: Development Status :: 3 - Alpha
Classifier: Environment :: Web Environment
Classifier: Framework :: Django
Classifier: Intended Audience :: Developers
Classifier: License :: OSI Approved :: MIT License
Classifier: Operating System :: OS Independent
Classifier: Programming Language :: Python
Classifier: Topic :: Internet :: WWW/HTTP
Classifier: Topic :: Internet :: WWW/HTTP :: Dynamic Content
Classifier: Topic :: Internet :: WWW/HTTP :: WSGI
Classifier: Topic :: Software Development :: Libraries :: Application Frameworks
Classifier: Topic :: Software Development :: Libraries :: Python Modules
